{
  "NULL_RATIO": 1.2,
  "class_id": "INDEPENDENT_OPPORTUNITY_DENSITY_CONSISTENCY_ASSEMBLY_V1",
  "evidence_strength": "ARTEFACT",
  "exact_one_sided_binomial_p_value": 0.7574336943091392,
  "family_green": false,
  "maximum_NULL_RATIO": 0.8,
  "null_candidate_count": 22,
  "null_exact_replay_missing_count": 0,
  "null_pass_count": 6,
  "null_pass_rate": 0.2727272727272727,
  "real_candidate_count": 22,
  "real_exact_replay_missing_count": 0,
  "real_pass_count": 5,
  "real_pass_rate": 0.22727272727272727,
  "thresholds_changed_after_outcome": false,
  "verdict": "ARTEFACT_GEOMETRY_ONLY"
}
